{
    "aliveOnly": true,
    "altKey": [["KEY_LALT", "KEY_RALT"]],
    "compareValues": {
        "equal": {
            "color": "#FFFFFF",
            "delim": "="
        },
        "lessThan": {
            "color": "#00FF00",
            "delim": "&lt;"
        },
        "moreThan": {
            "color": "#FF0000",
            "delim": "&gt;"
        }
    },
    "delay": 5,
    "enabled": true,
    "format": "<font face='$FieldFont' size='16' color='#FFFFFF'><b>Tank: <font color='#C3C3C3'>{{vehicle_name}}</font></font>\nReload: <font color='#14AFF1'>{{gun_reload_equip}} sec.</font>\nView Range: <font color='#96CC29'>{{vision_radius}} mt.</font>",
    "panelSize": {
        "height": 70.0,
        "width": 150.0
    },
    "showFor": 2,
    "textLock": false,
    "textPosition": {
        "alignX": "center",
        "alignY": "center",
        "x": -742.0,
        "y": 277.0
    },
    "textShadow": {
        "alpha": 0.8,
        "angle": 90,
        "blurX": 5,
        "blurY": 5,
        "color": "#000000",
        "distance": 1,
        "enabled": true,
        "quality": 2,
        "strength": 2
    },
    "version": 175
}